{
  "schema_version": "coco_capture_flow_validation.v1",
  "generated_at": "2026-04-27T14:46:27+00:00",
  "batch_size": 10,
  "input_total": 10,
  "processed_total": 10,
  "summary": {
    "total": 10,
    "ok": 10,
    "review": 0,
    "non_problem": 0,
    "error": 0,
    "issue_counts": {},
    "by_band": {
      "초등": {
        "ok": 10
      }
    },
    "by_source_kind": {
      "coco_app_capture": {
        "ok": 10
      }
    },
    "by_topic": {
      "arithmetic": {
        "ok": 8
      },
      "fraction_ratio": {
        "ok": 1
      },
      "pattern": {
        "ok": 1
      }
    }
  },
  "issue_examples": {},
  "results": [
    {
      "index": 601,
      "case_id": "초1-2_5단원_시계보기와규칙찾기_3회_p03_capture_q03",
      "band": "초등",
      "grade": 1,
      "source_kind": "coco_app_capture",
      "image_path": "/Users/juhwigeun/Library/Application Support/CocoAIStudy/captures/validation_segments/ba312f4157d9/초1-2_5단원_시계보기와규칙찾기_3회_p03_문항03.png",
      "relative_path": "/Users/juhwigeun/Library/Application Support/CocoAIStudy/captures/validation_segments/ba312f4157d9/초1-2_5단원_시계보기와규칙찾기_3회_p03_문항03.png",
      "pdf_path": "02.학습문제/05.문제은행/01.초등/1학년/PDF/skai_0105_무료_수학프린트_학습지_[단원평가_3회]_초1-2_Ⅴ._시계_보기와_규칙_찾기_[무료_수학_프린트_학습지_-_단원평가]_초등___초1-2-5.시계_보기와_규칙_찾기_[3회].pdf",
      "title_slug": "초1-2_5단원_시계보기와규칙찾기_3회",
      "source_page": 3,
      "page_count": 4,
      "parent_page_index": 80,
      "parent_relative_path": "02.학습문제/05.문제은행/01.초등/1학년/EDITE/초1-2_5단원_시계보기와규칙찾기_3회_p03.png",
      "problem_card_index": 3,
      "problem_card_label": "03",
      "problem_card_bbox": [
        0,
        802,
        671,
        1173
      ],
      "expected_problem_number": 20,
      "capture_file_id": "bd7487a45c60",
      "capture_file_name": "capture_00601_초1-2_5단원_시계보기와규칙찾기_3회_p03_문항03.png",
      "capture_path": "/Users/juhwigeun/Library/Application Support/CocoAIStudy/captures/validation/capture_00601_초1-2_5단원_시계보기와규칙찾기_3회_p03_문항03.png",
      "upload_path": "/Users/juhwigeun/Library/Application Support/CocoAIStudy/uploads/bd7487a45c60_capture_00601_초1-2_5단원_시계보기와규칙찾기_3회_p03_문항03.png",
      "upload_relative_path": "/Users/juhwigeun/Library/Application Support/CocoAIStudy/uploads/bd7487a45c60_capture_00601_초1-2_5단원_시계보기와규칙찾기_3회_p03_문항03.png",
      "status": "ok",
      "issues": [],
      "math_topic": "pattern",
      "display_topic": "pattern",
      "problem_text": "색칠한 수는 11부터 시작하여 몇씩 커지는지 구하세요.",
      "expressions": [
        "answer=3"
      ],
      "computed_answer": "3",
      "matched_choice": "",
      "solver_name": "table_lookup_solver",
      "validation_status": "verified",
      "problem_number": 20,
      "reference_answer": "3",
      "pdf_card_text": "20. 색칠한 수에 있는 규칙을 찾아 안에 알 맞은 수를 넣으세요.",
      "source_preview": "색칠한 수는 11부터 시작하여 몇씩 커지는지 구하세요. 19. 승준이는 4시 30분에 축구를 시작하여 시계 19. 승준이는 4시 30분에 축구를 시작하여 시계",
      "elapsed_seconds": 0.782
    },
    {
      "index": 602,
      "case_id": "초1-2_5단원_시계보기와규칙찾기_3회_p03_capture_q04",
      "band": "초등",
      "grade": 1,
      "source_kind": "coco_app_capture",
      "image_path": "/Users/juhwigeun/Library/Application Support/CocoAIStudy/captures/validation_segments/ba312f4157d9/초1-2_5단원_시계보기와규칙찾기_3회_p03_문항04.png",
      "relative_path": "/Users/juhwigeun/Library/Application Support/CocoAIStudy/captures/validation_segments/ba312f4157d9/초1-2_5단원_시계보기와규칙찾기_3회_p03_문항04.png",
      "pdf_path": "02.학습문제/05.문제은행/01.초등/1학년/PDF/skai_0105_무료_수학프린트_학습지_[단원평가_3회]_초1-2_Ⅴ._시계_보기와_규칙_찾기_[무료_수학_프린트_학습지_-_단원평가]_초등___초1-2-5.시계_보기와_규칙_찾기_[3회].pdf",
      "title_slug": "초1-2_5단원_시계보기와규칙찾기_3회",
      "source_page": 3,
      "page_count": 4,
      "parent_page_index": 80,
      "parent_relative_path": "02.학습문제/05.문제은행/01.초등/1학년/EDITE/초1-2_5단원_시계보기와규칙찾기_3회_p03.png",
      "problem_card_index": 4,
      "problem_card_label": "04",
      "problem_card_bbox": [
        0,
        1173,
        671,
        1644
      ],
      "expected_problem_number": 21,
      "capture_file_id": "8363e6c69c19",
      "capture_file_name": "capture_00602_초1-2_5단원_시계보기와규칙찾기_3회_p03_문항04.png",
      "capture_path": "/Users/juhwigeun/Library/Application Support/CocoAIStudy/captures/validation/capture_00602_초1-2_5단원_시계보기와규칙찾기_3회_p03_문항04.png",
      "upload_path": "/Users/juhwigeun/Library/Application Support/CocoAIStudy/uploads/8363e6c69c19_capture_00602_초1-2_5단원_시계보기와규칙찾기_3회_p03_문항04.png",
      "upload_relative_path": "/Users/juhwigeun/Library/Application Support/CocoAIStudy/uploads/8363e6c69c19_capture_00602_초1-2_5단원_시계보기와규칙찾기_3회_p03_문항04.png",
      "status": "ok",
      "issues": [],
      "math_topic": "pattern",
      "display_topic": "fraction_ratio",
      "problem_text": "answer=28",
      "expressions": [
        "answer=28",
        "11 12,13 14/15 16 17 18 19120",
        "2! 02193 94195 36 37 38 37/40"
      ],
      "computed_answer": "28",
      "matched_choice": "",
      "solver_name": "table_lookup_solver",
      "validation_status": "verified",
      "problem_number": 21,
      "reference_answer": "",
      "pdf_card_text": "색칠한 수는 11 부터 시작하여 씩 커집니다.",
      "source_preview": "answer=28 20, 색칠한 수에 있는 규칙을 찾아 | | 안에 알 11 12,13 14/15 16 17 18 19120 21 22 23 24 25 26 27 28 29 30 31 32 33 34 35 36 37 38 39 40 11부터 시작하여 | ㆍ |씩 커집니다. 20, 색칠한 수에 있는 규칙을 찾아 [ | 안에 알 11 12113 14115 16 17 18 19120 21 2...",
      "elapsed_seconds": 0.661
    },
    {
      "index": 603,
      "case_id": "초1-2_6단원_덧셈과뺄셈(3)_1회_p01_capture_q01",
      "band": "초등",
      "grade": 1,
      "source_kind": "coco_app_capture",
      "image_path": "/Users/juhwigeun/Library/Application Support/CocoAIStudy/captures/validation_segments/e719edfa8923/초1-2_6단원_덧셈과뺄셈_3__1회_p01_문항01.png",
      "relative_path": "/Users/juhwigeun/Library/Application Support/CocoAIStudy/captures/validation_segments/e719edfa8923/초1-2_6단원_덧셈과뺄셈_3__1회_p01_문항01.png",
      "pdf_path": "02.학습문제/05.문제은행/01.초등/1학년/PDF/skai_0104_무료_수학프린트_학습지_[단원평가_1회]_초1-2_Ⅵ._덧셈과_뺄셈(3)_[무료_수학_프린트_학습지_-_단원평가]_초등_1학년__초1-2-6.덧셈과_뺄셈(3)_[1회].pdf",
      "title_slug": "초1-2_6단원_덧셈과뺄셈(3)_1회",
      "source_page": 1,
      "page_count": 3,
      "parent_page_index": 81,
      "parent_relative_path": "02.학습문제/05.문제은행/01.초등/1학년/EDITE/초1-2_6단원_덧셈과뺄셈(3)_1회_p01.png",
      "problem_card_index": 1,
      "problem_card_label": "01",
      "problem_card_bbox": [
        0,
        0,
        677,
        349
      ],
      "expected_problem_number": 1,
      "capture_file_id": "6ea7a003fd72",
      "capture_file_name": "capture_00603_초1-2_6단원_덧셈과뺄셈_3__1회_p01_문항01.png",
      "capture_path": "/Users/juhwigeun/Library/Application Support/CocoAIStudy/captures/validation/capture_00603_초1-2_6단원_덧셈과뺄셈_3__1회_p01_문항01.png",
      "upload_path": "/Users/juhwigeun/Library/Application Support/CocoAIStudy/uploads/6ea7a003fd72_capture_00603_초1-2_6단원_덧셈과뺄셈_3__1회_p01_문항01.png",
      "upload_relative_path": "/Users/juhwigeun/Library/Application Support/CocoAIStudy/uploads/6ea7a003fd72_capture_00603_초1-2_6단원_덧셈과뺄셈_3__1회_p01_문항01.png",
      "status": "ok",
      "issues": [],
      "math_topic": "arithmetic",
      "display_topic": "arithmetic",
      "problem_text": "10을 이용하여 모으기와 가르기를 한 것입니다. 빈칸에 알맞은 수를 넣으세요.",
      "expressions": [
        "answer_text=빈칸: 12, 12, 2",
        "answer=3"
      ],
      "computed_answer": "빈칸: 12, 12, 2",
      "matched_choice": "",
      "solver_name": "visual_template_solver",
      "validation_status": "verified",
      "problem_number": 1,
      "reference_answer": "(왼쪽부터) 12, 12, 2",
      "pdf_card_text": "1. 1 을 이용하여 모으기와 가르기를 한 것입니 다. 빈칸에 알맞은 수를 넣어 보세요.",
      "source_preview": "10을 이용하여 모으기와 가르기를 한 것입니다. 빈칸에 알맞은 수를 넣으세요. ㅣ, 10을 이용하여 모으기와 가르기를 한 AGU 다. 빈칸에 알맞은 수를 넣어 보세요. 5 7 10 5So ㅣ. 10을 이용하여 모으기와 가르기를 한 것입니 | ㅣ, 10을 이용하여 모으기와 가르기를 한 AGU 다. 빈칸에 알맞은 수를 넣어 보세요. 5 7 10 5So ㅣ. 10을 이용하여 모으기와 가르기를...",
      "elapsed_seconds": 0.653
    },
    {
      "index": 604,
      "case_id": "초1-2_6단원_덧셈과뺄셈(3)_1회_p01_capture_q02",
      "band": "초등",
      "grade": 1,
      "source_kind": "coco_app_capture",
      "image_path": "/Users/juhwigeun/Library/Application Support/CocoAIStudy/captures/validation_segments/e719edfa8923/초1-2_6단원_덧셈과뺄셈_3__1회_p01_문항02.png",
      "relative_path": "/Users/juhwigeun/Library/Application Support/CocoAIStudy/captures/validation_segments/e719edfa8923/초1-2_6단원_덧셈과뺄셈_3__1회_p01_문항02.png",
      "pdf_path": "02.학습문제/05.문제은행/01.초등/1학년/PDF/skai_0104_무료_수학프린트_학습지_[단원평가_1회]_초1-2_Ⅵ._덧셈과_뺄셈(3)_[무료_수학_프린트_학습지_-_단원평가]_초등_1학년__초1-2-6.덧셈과_뺄셈(3)_[1회].pdf",
      "title_slug": "초1-2_6단원_덧셈과뺄셈(3)_1회",
      "source_page": 1,
      "page_count": 3,
      "parent_page_index": 81,
      "parent_relative_path": "02.학습문제/05.문제은행/01.초등/1학년/EDITE/초1-2_6단원_덧셈과뺄셈(3)_1회_p01.png",
      "problem_card_index": 2,
      "problem_card_label": "02",
      "problem_card_bbox": [
        0,
        349,
        677,
        647
      ],
      "expected_problem_number": 2,
      "capture_file_id": "3c91e2ac9813",
      "capture_file_name": "capture_00604_초1-2_6단원_덧셈과뺄셈_3__1회_p01_문항02.png",
      "capture_path": "/Users/juhwigeun/Library/Application Support/CocoAIStudy/captures/validation/capture_00604_초1-2_6단원_덧셈과뺄셈_3__1회_p01_문항02.png",
      "upload_path": "/Users/juhwigeun/Library/Application Support/CocoAIStudy/uploads/3c91e2ac9813_capture_00604_초1-2_6단원_덧셈과뺄셈_3__1회_p01_문항02.png",
      "upload_relative_path": "/Users/juhwigeun/Library/Application Support/CocoAIStudy/uploads/3c91e2ac9813_capture_00604_초1-2_6단원_덧셈과뺄셈_3__1회_p01_문항02.png",
      "status": "ok",
      "issues": [],
      "math_topic": "arithmetic",
      "display_topic": "arithmetic",
      "problem_text": "16 - 9의 빈칸에 알맞은 수를 써넣으세요.",
      "expressions": [
        "answer_text=빈칸: 7, 6",
        "16-9ㅋ |"
      ],
      "computed_answer": "빈칸: 7, 6",
      "matched_choice": "",
      "solver_name": "visual_template_solver",
      "validation_status": "verified",
      "problem_number": 2,
      "reference_answer": "(위에서부터) 7, 6",
      "pdf_card_text": "2. 안에 알맞은 수를 써넣으시오.",
      "source_preview": "16 - 9의 빈칸에 알맞은 수를 써넣으세요. 2. | ㅣ 안에 알맞은 수를 써넣으시오. 16-9ㅋ | 2 3 / 18 2. | ㅣ 안에 알맞은 수를 써넣으시오. 16-9ㅋ | 2 3 / 18",
      "elapsed_seconds": 0.407
    },
    {
      "index": 605,
      "case_id": "초1-2_6단원_덧셈과뺄셈(3)_1회_p01_capture_q03",
      "band": "초등",
      "grade": 1,
      "source_kind": "coco_app_capture",
      "image_path": "/Users/juhwigeun/Library/Application Support/CocoAIStudy/captures/validation_segments/e719edfa8923/초1-2_6단원_덧셈과뺄셈_3__1회_p01_문항03.png",
      "relative_path": "/Users/juhwigeun/Library/Application Support/CocoAIStudy/captures/validation_segments/e719edfa8923/초1-2_6단원_덧셈과뺄셈_3__1회_p01_문항03.png",
      "pdf_path": "02.학습문제/05.문제은행/01.초등/1학년/PDF/skai_0104_무료_수학프린트_학습지_[단원평가_1회]_초1-2_Ⅵ._덧셈과_뺄셈(3)_[무료_수학_프린트_학습지_-_단원평가]_초등_1학년__초1-2-6.덧셈과_뺄셈(3)_[1회].pdf",
      "title_slug": "초1-2_6단원_덧셈과뺄셈(3)_1회",
      "source_page": 1,
      "page_count": 3,
      "parent_page_index": 81,
      "parent_relative_path": "02.학습문제/05.문제은행/01.초등/1학년/EDITE/초1-2_6단원_덧셈과뺄셈(3)_1회_p01.png",
      "problem_card_index": 3,
      "problem_card_label": "03",
      "problem_card_bbox": [
        0,
        647,
        677,
        957
      ],
      "expected_problem_number": 3,
      "capture_file_id": "b3582ed9e74e",
      "capture_file_name": "capture_00605_초1-2_6단원_덧셈과뺄셈_3__1회_p01_문항03.png",
      "capture_path": "/Users/juhwigeun/Library/Application Support/CocoAIStudy/captures/validation/capture_00605_초1-2_6단원_덧셈과뺄셈_3__1회_p01_문항03.png",
      "upload_path": "/Users/juhwigeun/Library/Application Support/CocoAIStudy/uploads/b3582ed9e74e_capture_00605_초1-2_6단원_덧셈과뺄셈_3__1회_p01_문항03.png",
      "upload_relative_path": "/Users/juhwigeun/Library/Application Support/CocoAIStudy/uploads/b3582ed9e74e_capture_00605_초1-2_6단원_덧셈과뺄셈_3__1회_p01_문항03.png",
      "status": "ok",
      "issues": [],
      "math_topic": "arithmetic",
      "display_topic": "arithmetic",
      "problem_text": "6 + 5의 빈칸에 알맞은 수를 써넣으세요.",
      "expressions": [
        "answer_text=빈칸: 11, 1",
        "6+ 5=",
        "6+ 5"
      ],
      "computed_answer": "빈칸: 11, 1",
      "matched_choice": "",
      "solver_name": "visual_template_solver",
      "validation_status": "verified",
      "problem_number": 3,
      "reference_answer": "(위에서부터) 11, 1",
      "pdf_card_text": "3. 안에 알맞은 수를 써넣으시오.",
      "source_preview": "6 + 5의 빈칸에 알맞은 수를 써넣으세요. 3.) 안에 알맞은 수를 써넣으시오. 6+ 5= 4 3. | ㅣ 안에 알맞은 +B 써넣으시오. 6+ 5 4 | | 3. ㅣ | 안에 알맞은 수를 써넣으시오. 3.) 안에 알맞은 수를 써넣으시오. 6+ 5= 4 3. | ㅣ 안에 알맞은 +B 써넣으시오. 6+ 5 4 | | 3. ㅣ | 안에 알맞은 수를 써넣으시오.",
      "elapsed_seconds": 0.393
    },
    {
      "index": 606,
      "case_id": "초1-2_6단원_덧셈과뺄셈(3)_1회_p01_capture_q04",
      "band": "초등",
      "grade": 1,
      "source_kind": "coco_app_capture",
      "image_path": "/Users/juhwigeun/Library/Application Support/CocoAIStudy/captures/validation_segments/e719edfa8923/초1-2_6단원_덧셈과뺄셈_3__1회_p01_문항04.png",
      "relative_path": "/Users/juhwigeun/Library/Application Support/CocoAIStudy/captures/validation_segments/e719edfa8923/초1-2_6단원_덧셈과뺄셈_3__1회_p01_문항04.png",
      "pdf_path": "02.학습문제/05.문제은행/01.초등/1학년/PDF/skai_0104_무료_수학프린트_학습지_[단원평가_1회]_초1-2_Ⅵ._덧셈과_뺄셈(3)_[무료_수학_프린트_학습지_-_단원평가]_초등_1학년__초1-2-6.덧셈과_뺄셈(3)_[1회].pdf",
      "title_slug": "초1-2_6단원_덧셈과뺄셈(3)_1회",
      "source_page": 1,
      "page_count": 3,
      "parent_page_index": 81,
      "parent_relative_path": "02.학습문제/05.문제은행/01.초등/1학년/EDITE/초1-2_6단원_덧셈과뺄셈(3)_1회_p01.png",
      "problem_card_index": 4,
      "problem_card_label": "04",
      "problem_card_bbox": [
        0,
        957,
        677,
        1260
      ],
      "expected_problem_number": 4,
      "capture_file_id": "9fff80532e12",
      "capture_file_name": "capture_00606_초1-2_6단원_덧셈과뺄셈_3__1회_p01_문항04.png",
      "capture_path": "/Users/juhwigeun/Library/Application Support/CocoAIStudy/captures/validation/capture_00606_초1-2_6단원_덧셈과뺄셈_3__1회_p01_문항04.png",
      "upload_path": "/Users/juhwigeun/Library/Application Support/CocoAIStudy/uploads/9fff80532e12_capture_00606_초1-2_6단원_덧셈과뺄셈_3__1회_p01_문항04.png",
      "upload_relative_path": "/Users/juhwigeun/Library/Application Support/CocoAIStudy/uploads/9fff80532e12_capture_00606_초1-2_6단원_덧셈과뺄셈_3__1회_p01_문항04.png",
      "status": "ok",
      "issues": [],
      "math_topic": "arithmetic",
      "display_topic": "arithmetic",
      "problem_text": "5S+7 7+6",
      "expressions": [
        "5S+7 7+6",
        "8+3 3+8"
      ],
      "computed_answer": "49",
      "matched_choice": "",
      "solver_name": "safe_eval_solver",
      "validation_status": "verified",
      "problem_number": 4,
      "reference_answer": "",
      "pdf_card_text": "5. 뺄셈을 해 보세요. 15 + 6 -",
      "source_preview": "5S+7 7+6 4. 합이 11인 덧셈식을 모두 찾아 색칠해 보세요. 8+3 3+8 5S+7 7+6 4, 합이 1191 덧셈식을 모두 찾아 색칠해 보세요. 4, 합이 11인 덧셈식을 모두 찾아 색칠해 보세요. ， 4. 합이 11인 덧셈식을 모두 찾아 색칠해 보세요. 8+3 3+8 5S+7 7+6 4, 합이 1191 덧셈식을 모두 찾아 색칠해 보세요. 4, 합이 11인 덧셈식을 모두 찾아...",
      "elapsed_seconds": 0.418
    },
    {
      "index": 607,
      "case_id": "초1-2_6단원_덧셈과뺄셈(3)_1회_p01_capture_q05",
      "band": "초등",
      "grade": 1,
      "source_kind": "coco_app_capture",
      "image_path": "/Users/juhwigeun/Library/Application Support/CocoAIStudy/captures/validation_segments/e719edfa8923/초1-2_6단원_덧셈과뺄셈_3__1회_p01_문항05.png",
      "relative_path": "/Users/juhwigeun/Library/Application Support/CocoAIStudy/captures/validation_segments/e719edfa8923/초1-2_6단원_덧셈과뺄셈_3__1회_p01_문항05.png",
      "pdf_path": "02.학습문제/05.문제은행/01.초등/1학년/PDF/skai_0104_무료_수학프린트_학습지_[단원평가_1회]_초1-2_Ⅵ._덧셈과_뺄셈(3)_[무료_수학_프린트_학습지_-_단원평가]_초등_1학년__초1-2-6.덧셈과_뺄셈(3)_[1회].pdf",
      "title_slug": "초1-2_6단원_덧셈과뺄셈(3)_1회",
      "source_page": 1,
      "page_count": 3,
      "parent_page_index": 81,
      "parent_relative_path": "02.학습문제/05.문제은행/01.초등/1학년/EDITE/초1-2_6단원_덧셈과뺄셈(3)_1회_p01.png",
      "problem_card_index": 5,
      "problem_card_label": "05",
      "problem_card_bbox": [
        0,
        1260,
        677,
        1470
      ],
      "expected_problem_number": 5,
      "capture_file_id": "f0edc3a8eca4",
      "capture_file_name": "capture_00607_초1-2_6단원_덧셈과뺄셈_3__1회_p01_문항05.png",
      "capture_path": "/Users/juhwigeun/Library/Application Support/CocoAIStudy/captures/validation/capture_00607_초1-2_6단원_덧셈과뺄셈_3__1회_p01_문항05.png",
      "upload_path": "/Users/juhwigeun/Library/Application Support/CocoAIStudy/uploads/f0edc3a8eca4_capture_00607_초1-2_6단원_덧셈과뺄셈_3__1회_p01_문항05.png",
      "upload_relative_path": "/Users/juhwigeun/Library/Application Support/CocoAIStudy/uploads/f0edc3a8eca4_capture_00607_초1-2_6단원_덧셈과뺄셈_3__1회_p01_문항05.png",
      "status": "ok",
      "issues": [],
      "math_topic": "arithmetic",
      "display_topic": "arithmetic",
      "problem_text": "15 - 6의 값을 구하세요.",
      "expressions": [
        "answer=9",
        "5-6=[ |",
        "6-6=[ |",
        "8-0-[ |"
      ],
      "computed_answer": "9",
      "matched_choice": "",
      "solver_name": "table_lookup_solver",
      "validation_status": "verified",
      "problem_number": 5,
      "reference_answer": "9",
      "pdf_card_text": "",
      "source_preview": "15 - 6의 값을 구하세요. 5 . WHS 해 보세요. 5-6=[ | 5 . wale 해 보세요. 8-0-[ | 6-6=[ | 5 . WHS 해 보세요. 5-6=[ | 5 . wale 해 보세요. 8-0-[ | 6-6=[ |",
      "elapsed_seconds": 0.331
    },
    {
      "index": 608,
      "case_id": "초1-2_6단원_덧셈과뺄셈(3)_1회_p01_capture_q06",
      "band": "초등",
      "grade": 1,
      "source_kind": "coco_app_capture",
      "image_path": "/Users/juhwigeun/Library/Application Support/CocoAIStudy/captures/validation_segments/e719edfa8923/초1-2_6단원_덧셈과뺄셈_3__1회_p01_문항06.png",
      "relative_path": "/Users/juhwigeun/Library/Application Support/CocoAIStudy/captures/validation_segments/e719edfa8923/초1-2_6단원_덧셈과뺄셈_3__1회_p01_문항06.png",
      "pdf_path": "02.학습문제/05.문제은행/01.초등/1학년/PDF/skai_0104_무료_수학프린트_학습지_[단원평가_1회]_초1-2_Ⅵ._덧셈과_뺄셈(3)_[무료_수학_프린트_학습지_-_단원평가]_초등_1학년__초1-2-6.덧셈과_뺄셈(3)_[1회].pdf",
      "title_slug": "초1-2_6단원_덧셈과뺄셈(3)_1회",
      "source_page": 1,
      "page_count": 3,
      "parent_page_index": 81,
      "parent_relative_path": "02.학습문제/05.문제은행/01.초등/1학년/EDITE/초1-2_6단원_덧셈과뺄셈(3)_1회_p01.png",
      "problem_card_index": 6,
      "problem_card_label": "06",
      "problem_card_bbox": [
        649,
        0,
        1326,
        436
      ],
      "expected_problem_number": 6,
      "capture_file_id": "8576c5c2edf8",
      "capture_file_name": "capture_00608_초1-2_6단원_덧셈과뺄셈_3__1회_p01_문항06.png",
      "capture_path": "/Users/juhwigeun/Library/Application Support/CocoAIStudy/captures/validation/capture_00608_초1-2_6단원_덧셈과뺄셈_3__1회_p01_문항06.png",
      "upload_path": "/Users/juhwigeun/Library/Application Support/CocoAIStudy/uploads/8576c5c2edf8_capture_00608_초1-2_6단원_덧셈과뺄셈_3__1회_p01_문항06.png",
      "upload_relative_path": "/Users/juhwigeun/Library/Application Support/CocoAIStudy/uploads/8576c5c2edf8_capture_00608_초1-2_6단원_덧셈과뺄셈_3__1회_p01_문항06.png",
      "status": "ok",
      "issues": [],
      "math_topic": "arithmetic",
      "display_topic": "arithmetic",
      "problem_text": "5 + 9의 값을 구하세요.",
      "expressions": [
        "answer=14",
        "5+9=| |",
        "5+9=[ |"
      ],
      "computed_answer": "14",
      "matched_choice": "",
      "solver_name": "table_lookup_solver",
      "validation_status": "verified",
      "problem_number": 6,
      "reference_answer": "14",
      "pdf_card_text": "초 1-2 이름 : 덧셈과 뺄셈(3) 점수 : 6. 덧셈을 해 보세요.",
      "source_preview": "5 + 9의 값을 구하세요. 6, 덧셈을 해 보세요. | | | | '의의의의 - 5+9=| | 의99990nb 5+9=[ | 6, 덧셈을 해 보세요. | | | | '의의의의 - 5+9=| | 의99990nb 5+9=[ |",
      "elapsed_seconds": 0.834
    },
    {
      "index": 609,
      "case_id": "초1-2_6단원_덧셈과뺄셈(3)_1회_p01_capture_q07",
      "band": "초등",
      "grade": 1,
      "source_kind": "coco_app_capture",
      "image_path": "/Users/juhwigeun/Library/Application Support/CocoAIStudy/captures/validation_segments/e719edfa8923/초1-2_6단원_덧셈과뺄셈_3__1회_p01_문항07.png",
      "relative_path": "/Users/juhwigeun/Library/Application Support/CocoAIStudy/captures/validation_segments/e719edfa8923/초1-2_6단원_덧셈과뺄셈_3__1회_p01_문항07.png",
      "pdf_path": "02.학습문제/05.문제은행/01.초등/1학년/PDF/skai_0104_무료_수학프린트_학습지_[단원평가_1회]_초1-2_Ⅵ._덧셈과_뺄셈(3)_[무료_수학_프린트_학습지_-_단원평가]_초등_1학년__초1-2-6.덧셈과_뺄셈(3)_[1회].pdf",
      "title_slug": "초1-2_6단원_덧셈과뺄셈(3)_1회",
      "source_page": 1,
      "page_count": 3,
      "parent_page_index": 81,
      "parent_relative_path": "02.학습문제/05.문제은행/01.초등/1학년/EDITE/초1-2_6단원_덧셈과뺄셈(3)_1회_p01.png",
      "problem_card_index": 7,
      "problem_card_label": "07",
      "problem_card_bbox": [
        649,
        436,
        1326,
        655
      ],
      "expected_problem_number": 7,
      "capture_file_id": "c2119a30f165",
      "capture_file_name": "capture_00609_초1-2_6단원_덧셈과뺄셈_3__1회_p01_문항07.png",
      "capture_path": "/Users/juhwigeun/Library/Application Support/CocoAIStudy/captures/validation/capture_00609_초1-2_6단원_덧셈과뺄셈_3__1회_p01_문항07.png",
      "upload_path": "/Users/juhwigeun/Library/Application Support/CocoAIStudy/uploads/c2119a30f165_capture_00609_초1-2_6단원_덧셈과뺄셈_3__1회_p01_문항07.png",
      "upload_relative_path": "/Users/juhwigeun/Library/Application Support/CocoAIStudy/uploads/c2119a30f165_capture_00609_초1-2_6단원_덧셈과뺄셈_3__1회_p01_문항07.png",
      "status": "ok",
      "issues": [],
      "math_topic": "arithmetic",
      "display_topic": "arithmetic",
      "problem_text": "8 + □ = 15에서 □ 안에 알맞은 수를 쓰세요.",
      "expressions": [
        "answer=7",
        "s+[]=15",
        "*(3"
      ],
      "computed_answer": "7",
      "matched_choice": "",
      "solver_name": "table_lookup_solver",
      "validation_status": "verified",
      "problem_number": 7,
      "reference_answer": "7",
      "pdf_card_text": "59 - 7. 안에 알맞은 수를 써 넣으세요. 8 - 15",
      "source_preview": "8 + □ = 15에서 □ 안에 알맞은 수를 쓰세요. 7. [ ㅣ 안에 알맞은 수를 써 Youle. s+[]=15 7. [ ㅣ 안에 알맞은 수를 써 넣으세요. “(3 7. | | 안에 알맞은 수를 써 넣으세요. 7. [ ㅣ 안에 알맞은 수를 써 Youle. s+[]=15 7. [ ㅣ 안에 알맞은 수를 써 넣으세요. “(3 7. | | 안에 알맞은 수를 써 넣으세요.",
      "elapsed_seconds": 0.41
    },
    {
      "index": 610,
      "case_id": "초1-2_6단원_덧셈과뺄셈(3)_1회_p01_capture_q08",
      "band": "초등",
      "grade": 1,
      "source_kind": "coco_app_capture",
      "image_path": "/Users/juhwigeun/Library/Application Support/CocoAIStudy/captures/validation_segments/e719edfa8923/초1-2_6단원_덧셈과뺄셈_3__1회_p01_문항08.png",
      "relative_path": "/Users/juhwigeun/Library/Application Support/CocoAIStudy/captures/validation_segments/e719edfa8923/초1-2_6단원_덧셈과뺄셈_3__1회_p01_문항08.png",
      "pdf_path": "02.학습문제/05.문제은행/01.초등/1학년/PDF/skai_0104_무료_수학프린트_학습지_[단원평가_1회]_초1-2_Ⅵ._덧셈과_뺄셈(3)_[무료_수학_프린트_학습지_-_단원평가]_초등_1학년__초1-2-6.덧셈과_뺄셈(3)_[1회].pdf",
      "title_slug": "초1-2_6단원_덧셈과뺄셈(3)_1회",
      "source_page": 1,
      "page_count": 3,
      "parent_page_index": 81,
      "parent_relative_path": "02.학습문제/05.문제은행/01.초등/1학년/EDITE/초1-2_6단원_덧셈과뺄셈(3)_1회_p01.png",
      "problem_card_index": 8,
      "problem_card_label": "08",
      "problem_card_bbox": [
        649,
        655,
        1326,
        941
      ],
      "expected_problem_number": 8,
      "capture_file_id": "dacbd61dd00d",
      "capture_file_name": "capture_00610_초1-2_6단원_덧셈과뺄셈_3__1회_p01_문항08.png",
      "capture_path": "/Users/juhwigeun/Library/Application Support/CocoAIStudy/captures/validation/capture_00610_초1-2_6단원_덧셈과뺄셈_3__1회_p01_문항08.png",
      "upload_path": "/Users/juhwigeun/Library/Application Support/CocoAIStudy/uploads/dacbd61dd00d_capture_00610_초1-2_6단원_덧셈과뺄셈_3__1회_p01_문항08.png",
      "upload_relative_path": "/Users/juhwigeun/Library/Application Support/CocoAIStudy/uploads/dacbd61dd00d_capture_00610_초1-2_6단원_덧셈과뺄셈_3__1회_p01_문항08.png",
      "status": "ok",
      "issues": [],
      "math_topic": "arithmetic",
      "display_topic": "arithmetic",
      "problem_text": "6, 7, 5, 4 중 가장 작은 수와 가장 큰 수의 합을 구하세요.",
      "expressions": [
        "answer=11"
      ],
      "computed_answer": "11",
      "matched_choice": "",
      "solver_name": "table_lookup_solver",
      "validation_status": "verified",
      "problem_number": 8,
      "reference_answer": "11",
      "pdf_card_text": "8 - 15 8. 가장 작은 수와 가장 큰 수의 합을 구하시오. 6 7 5 4 ( )",
      "source_preview": "6, 7, 5, 4 중 가장 작은 수와 가장 큰 수의 합을 구하세요. 8. 가장 작은 수와 가장 큰 수의 합을 구하시오. ( 6 7 5 4 ) 6 7 5 4 @. 가장 작은 수와 가장 큰 수의 HS 구하시오. 8. 가장 작은 수와 가장 큰 수의 합을 구하시오. ( 6 7 5 4 ) 6 7 5 4 @. 가장 작은 수와 가장 큰 수의 HS 구하시오.",
      "elapsed_seconds": 0.467
    }
  ]
}