{
  "schema_version": "coco_capture_flow_validation.v1",
  "generated_at": "2026-04-27T14:51:34+00:00",
  "batch_size": 10,
  "input_total": 10,
  "processed_total": 10,
  "summary": {
    "total": 10,
    "ok": 10,
    "review": 0,
    "non_problem": 0,
    "error": 0,
    "issue_counts": {},
    "by_band": {
      "초등": {
        "ok": 10
      }
    },
    "by_source_kind": {
      "coco_app_capture": {
        "ok": 10
      }
    },
    "by_topic": {
      "arithmetic": {
        "ok": 9
      },
      "probability": {
        "ok": 1
      }
    }
  },
  "issue_examples": {},
  "results": [
    {
      "index": 611,
      "case_id": "초1-2_6단원_덧셈과뺄셈(3)_1회_p01_capture_q09",
      "band": "초등",
      "grade": 1,
      "source_kind": "coco_app_capture",
      "image_path": "/Users/juhwigeun/Library/Application Support/CocoAIStudy/captures/validation_segments/e719edfa8923/초1-2_6단원_덧셈과뺄셈_3__1회_p01_문항09.png",
      "relative_path": "/Users/juhwigeun/Library/Application Support/CocoAIStudy/captures/validation_segments/e719edfa8923/초1-2_6단원_덧셈과뺄셈_3__1회_p01_문항09.png",
      "pdf_path": "02.학습문제/05.문제은행/01.초등/1학년/PDF/skai_0104_무료_수학프린트_학습지_[단원평가_1회]_초1-2_Ⅵ._덧셈과_뺄셈(3)_[무료_수학_프린트_학습지_-_단원평가]_초등_1학년__초1-2-6.덧셈과_뺄셈(3)_[1회].pdf",
      "title_slug": "초1-2_6단원_덧셈과뺄셈(3)_1회",
      "source_page": 1,
      "page_count": 3,
      "parent_page_index": 81,
      "parent_relative_path": "02.학습문제/05.문제은행/01.초등/1학년/EDITE/초1-2_6단원_덧셈과뺄셈(3)_1회_p01.png",
      "problem_card_index": 9,
      "problem_card_label": "09",
      "problem_card_bbox": [
        649,
        941,
        1326,
        1247
      ],
      "expected_problem_number": 9,
      "capture_file_id": "7429a1a96ec9",
      "capture_file_name": "capture_00611_초1-2_6단원_덧셈과뺄셈_3__1회_p01_문항09.png",
      "capture_path": "/Users/juhwigeun/Library/Application Support/CocoAIStudy/captures/validation/capture_00611_초1-2_6단원_덧셈과뺄셈_3__1회_p01_문항09.png",
      "upload_path": "/Users/juhwigeun/Library/Application Support/CocoAIStudy/uploads/7429a1a96ec9_capture_00611_초1-2_6단원_덧셈과뺄셈_3__1회_p01_문항09.png",
      "upload_relative_path": "/Users/juhwigeun/Library/Application Support/CocoAIStudy/uploads/7429a1a96ec9_capture_00611_초1-2_6단원_덧셈과뺄셈_3__1회_p01_문항09.png",
      "status": "ok",
      "issues": [],
      "math_topic": "arithmetic",
      "display_topic": "arithmetic",
      "problem_text": "9에서 7을 더하고 8을 빼세요.",
      "expressions": [
        "answer_text=빈칸: 16, 8",
        "+7 -8"
      ],
      "computed_answer": "빈칸: 16, 8",
      "matched_choice": "",
      "solver_name": "visual_template_solver",
      "validation_status": "verified",
      "problem_number": 9,
      "reference_answer": "16, 8",
      "pdf_card_text": "10. 계산 결과를 비교하여 안에  , - ,  를 알맞게 써넣으세요. +",
      "source_preview": "9에서 7을 더하고 8을 빼세요. 9. 빈칸에 알맞은 수를 써넣으세요. +7 -8 9 9. 빈칸에 알맞은 수를 써넣으세요. +7 -8 9",
      "elapsed_seconds": 0.562
    },
    {
      "index": 612,
      "case_id": "초1-2_6단원_덧셈과뺄셈(3)_1회_p01_capture_q10",
      "band": "초등",
      "grade": 1,
      "source_kind": "coco_app_capture",
      "image_path": "/Users/juhwigeun/Library/Application Support/CocoAIStudy/captures/validation_segments/e719edfa8923/초1-2_6단원_덧셈과뺄셈_3__1회_p01_문항10.png",
      "relative_path": "/Users/juhwigeun/Library/Application Support/CocoAIStudy/captures/validation_segments/e719edfa8923/초1-2_6단원_덧셈과뺄셈_3__1회_p01_문항10.png",
      "pdf_path": "02.학습문제/05.문제은행/01.초등/1학년/PDF/skai_0104_무료_수학프린트_학습지_[단원평가_1회]_초1-2_Ⅵ._덧셈과_뺄셈(3)_[무료_수학_프린트_학습지_-_단원평가]_초등_1학년__초1-2-6.덧셈과_뺄셈(3)_[1회].pdf",
      "title_slug": "초1-2_6단원_덧셈과뺄셈(3)_1회",
      "source_page": 1,
      "page_count": 3,
      "parent_page_index": 81,
      "parent_relative_path": "02.학습문제/05.문제은행/01.초등/1학년/EDITE/초1-2_6단원_덧셈과뺄셈(3)_1회_p01.png",
      "problem_card_index": 10,
      "problem_card_label": "10",
      "problem_card_bbox": [
        649,
        1247,
        1326,
        1470
      ],
      "expected_problem_number": 10,
      "capture_file_id": "eb68ba69a696",
      "capture_file_name": "capture_00612_초1-2_6단원_덧셈과뺄셈_3__1회_p01_문항10.png",
      "capture_path": "/Users/juhwigeun/Library/Application Support/CocoAIStudy/captures/validation/capture_00612_초1-2_6단원_덧셈과뺄셈_3__1회_p01_문항10.png",
      "upload_path": "/Users/juhwigeun/Library/Application Support/CocoAIStudy/uploads/eb68ba69a696_capture_00612_초1-2_6단원_덧셈과뺄셈_3__1회_p01_문항10.png",
      "upload_relative_path": "/Users/juhwigeun/Library/Application Support/CocoAIStudy/uploads/eb68ba69a696_capture_00612_초1-2_6단원_덧셈과뺄셈_3__1회_p01_문항10.png",
      "status": "ok",
      "issues": [],
      "math_topic": "arithmetic",
      "display_topic": "arithmetic",
      "problem_text": "16 - 9와 5 + 6의 계산 결과를 비교하세요.",
      "expressions": [
        "answer_text=<",
        "16-9 ( ) 5+6"
      ],
      "computed_answer": "<",
      "matched_choice": "",
      "solver_name": "visual_template_solver",
      "validation_status": "verified",
      "problem_number": 10,
      "reference_answer": "",
      "pdf_card_text": "16 + 9 56",
      "source_preview": "16 - 9와 5 + 6의 계산 결과를 비교하세요. 10. 계산 결과를 비교하여 (_) 안에 >, =, < 16-9 ( ) 5+6 10. 계산 결과를 비교하여 C 안에 >, =, < 10. 계산 결과를 비교하여 (_) 안에 >, =, < 16-9 ( ) 5+6 10. 계산 결과를 비교하여 C 안에 >, =, <",
      "elapsed_seconds": 0.403
    },
    {
      "index": 613,
      "case_id": "초1-2_6단원_덧셈과뺄셈(3)_1회_p02_capture_q01",
      "band": "초등",
      "grade": 1,
      "source_kind": "coco_app_capture",
      "image_path": "/Users/juhwigeun/Library/Application Support/CocoAIStudy/captures/validation_segments/c42138729b20/초1-2_6단원_덧셈과뺄셈_3__1회_p02_문항01.png",
      "relative_path": "/Users/juhwigeun/Library/Application Support/CocoAIStudy/captures/validation_segments/c42138729b20/초1-2_6단원_덧셈과뺄셈_3__1회_p02_문항01.png",
      "pdf_path": "02.학습문제/05.문제은행/01.초등/1학년/PDF/skai_0104_무료_수학프린트_학습지_[단원평가_1회]_초1-2_Ⅵ._덧셈과_뺄셈(3)_[무료_수학_프린트_학습지_-_단원평가]_초등_1학년__초1-2-6.덧셈과_뺄셈(3)_[1회].pdf",
      "title_slug": "초1-2_6단원_덧셈과뺄셈(3)_1회",
      "source_page": 2,
      "page_count": 3,
      "parent_page_index": 82,
      "parent_relative_path": "02.학습문제/05.문제은행/01.초등/1학년/EDITE/초1-2_6단원_덧셈과뺄셈(3)_1회_p02.png",
      "problem_card_index": 1,
      "problem_card_label": "01",
      "problem_card_bbox": [
        0,
        0,
        677,
        609
      ],
      "expected_problem_number": 11,
      "capture_file_id": "e741c2b85c3f",
      "capture_file_name": "capture_00613_초1-2_6단원_덧셈과뺄셈_3__1회_p02_문항01.png",
      "capture_path": "/Users/juhwigeun/Library/Application Support/CocoAIStudy/captures/validation/capture_00613_초1-2_6단원_덧셈과뺄셈_3__1회_p02_문항01.png",
      "upload_path": "/Users/juhwigeun/Library/Application Support/CocoAIStudy/uploads/e741c2b85c3f_capture_00613_초1-2_6단원_덧셈과뺄셈_3__1회_p02_문항01.png",
      "upload_relative_path": "/Users/juhwigeun/Library/Application Support/CocoAIStudy/uploads/e741c2b85c3f_capture_00613_초1-2_6단원_덧셈과뺄셈_3__1회_p02_문항01.png",
      "status": "ok",
      "issues": [],
      "math_topic": "arithmetic",
      "display_topic": "arithmetic",
      "problem_text": "9 + 6, 8 + 6, 7 + 6, 6 + 6의 빈칸을 채우고 알맞은 말에 ○표 하세요.",
      "expressions": [
        "answer_text=15, 14, 13, 12 / 작아집니다에 ○표",
        "9+6=",
        "8+6=",
        "7+6=",
        "6+6="
      ],
      "computed_answer": "15, 14, 13, 12 / 작아집니다에 ○표",
      "matched_choice": "",
      "solver_name": "visual_template_solver",
      "validation_status": "verified",
      "problem_number": 11,
      "reference_answer": "15, 14, 13, 12 / ‘작아집니다’에 ○표",
      "pdf_card_text": "11. 안에 알맞은 수를 써넣고 알맞은 말에 ○표 하세요. ⇨ 1 씩 작아지는 수에 같은 수를 더하면 합은 1 씩 (작아집니다 / 커집니다).",
      "source_preview": "9 + 6, 8 + 6, 7 + 6, 6 + 6의 빈칸을 채우고 알맞은 말에 ○표 하세요. 9+6= 8+6= 7+6= 6+6= > 14 작아지는 수에 같은 +S 더하면 합은 1씩 (작아집니다 / 커집니다). 9+6=| | s+6=| | 7+6=[ | 6+6=| | > 1씩 작아지는 수에 같은 수를 더하면 8+6=| | 214 작아지는 40) 같은 수를 더하면 | 9+6= 8+6= 7+6...",
      "elapsed_seconds": 0.853
    },
    {
      "index": 614,
      "case_id": "초1-2_6단원_덧셈과뺄셈(3)_1회_p02_capture_q02",
      "band": "초등",
      "grade": 1,
      "source_kind": "coco_app_capture",
      "image_path": "/Users/juhwigeun/Library/Application Support/CocoAIStudy/captures/validation_segments/c42138729b20/초1-2_6단원_덧셈과뺄셈_3__1회_p02_문항02.png",
      "relative_path": "/Users/juhwigeun/Library/Application Support/CocoAIStudy/captures/validation_segments/c42138729b20/초1-2_6단원_덧셈과뺄셈_3__1회_p02_문항02.png",
      "pdf_path": "02.학습문제/05.문제은행/01.초등/1학년/PDF/skai_0104_무료_수학프린트_학습지_[단원평가_1회]_초1-2_Ⅵ._덧셈과_뺄셈(3)_[무료_수학_프린트_학습지_-_단원평가]_초등_1학년__초1-2-6.덧셈과_뺄셈(3)_[1회].pdf",
      "title_slug": "초1-2_6단원_덧셈과뺄셈(3)_1회",
      "source_page": 2,
      "page_count": 3,
      "parent_page_index": 82,
      "parent_relative_path": "02.학습문제/05.문제은행/01.초등/1학년/EDITE/초1-2_6단원_덧셈과뺄셈(3)_1회_p02.png",
      "problem_card_index": 2,
      "problem_card_label": "02",
      "problem_card_bbox": [
        0,
        609,
        677,
        1255
      ],
      "expected_problem_number": 12,
      "capture_file_id": "fb3374a9ca3c",
      "capture_file_name": "capture_00614_초1-2_6단원_덧셈과뺄셈_3__1회_p02_문항02.png",
      "capture_path": "/Users/juhwigeun/Library/Application Support/CocoAIStudy/captures/validation/capture_00614_초1-2_6단원_덧셈과뺄셈_3__1회_p02_문항02.png",
      "upload_path": "/Users/juhwigeun/Library/Application Support/CocoAIStudy/uploads/fb3374a9ca3c_capture_00614_초1-2_6단원_덧셈과뺄셈_3__1회_p02_문항02.png",
      "upload_relative_path": "/Users/juhwigeun/Library/Application Support/CocoAIStudy/uploads/fb3374a9ca3c_capture_00614_초1-2_6단원_덧셈과뺄셈_3__1회_p02_문항02.png",
      "status": "ok",
      "issues": [],
      "math_topic": "arithmetic",
      "display_topic": "arithmetic",
      "problem_text": "15 - 6, 15 - 7, 15 - 8, 15 - 9의 빈칸을 채우고 알맞은 말에 ○표 하세요.",
      "expressions": [
        "answer_text=9, 8, 7, 6 / 작아집니다에 ○표",
        "15-8=| _",
        "15-6=|",
        "15-7=|",
        "15-8=|"
      ],
      "computed_answer": "9, 8, 7, 6 / 작아집니다에 ○표",
      "matched_choice": "",
      "solver_name": "visual_template_solver",
      "validation_status": "verified",
      "problem_number": 12,
      "reference_answer": "9, 8, 7, 6 / ‘작아집니다’ 에 ○표",
      "pdf_card_text": "12. 안에 알맞은 수를 써넣고 알맞은 말에 ○표 하세요. ⇨ 같은 수에서 1 씩 커지는 수를 빼면 차는 1 씩 (작아집니다 / 커집니다).",
      "source_preview": "15 - 6, 15 - 7, 15 - 8, 15 - 9의 빈칸을 채우고 알맞은 말에 ○표 하세요. 12. | | 안에 알맞은 수를 써넣고 알맞은 말에 15-6=| 15-7=| 15-8=| 18-9=| .| > 같은 FOI 1씩 커지는 수를 빼면 차는 1씩 (작아집니다 / 커집니다). 12. [ | 안에 알맞은 수를 써넣고 알맞은 말에 15-9=| = 같은 수에서 1씩 커지는 수를 빼면 ...",
      "elapsed_seconds": 0.79
    },
    {
      "index": 615,
      "case_id": "초1-2_6단원_덧셈과뺄셈(3)_1회_p02_capture_q03",
      "band": "초등",
      "grade": 1,
      "source_kind": "coco_app_capture",
      "image_path": "/Users/juhwigeun/Library/Application Support/CocoAIStudy/captures/validation_segments/c42138729b20/초1-2_6단원_덧셈과뺄셈_3__1회_p02_문항03.png",
      "relative_path": "/Users/juhwigeun/Library/Application Support/CocoAIStudy/captures/validation_segments/c42138729b20/초1-2_6단원_덧셈과뺄셈_3__1회_p02_문항03.png",
      "pdf_path": "02.학습문제/05.문제은행/01.초등/1학년/PDF/skai_0104_무료_수학프린트_학습지_[단원평가_1회]_초1-2_Ⅵ._덧셈과_뺄셈(3)_[무료_수학_프린트_학습지_-_단원평가]_초등_1학년__초1-2-6.덧셈과_뺄셈(3)_[1회].pdf",
      "title_slug": "초1-2_6단원_덧셈과뺄셈(3)_1회",
      "source_page": 2,
      "page_count": 3,
      "parent_page_index": 82,
      "parent_relative_path": "02.학습문제/05.문제은행/01.초등/1학년/EDITE/초1-2_6단원_덧셈과뺄셈(3)_1회_p02.png",
      "problem_card_index": 3,
      "problem_card_label": "03",
      "problem_card_bbox": [
        0,
        1255,
        677,
        1804
      ],
      "expected_problem_number": 13,
      "capture_file_id": "6a7499b4ed4a",
      "capture_file_name": "capture_00615_초1-2_6단원_덧셈과뺄셈_3__1회_p02_문항03.png",
      "capture_path": "/Users/juhwigeun/Library/Application Support/CocoAIStudy/captures/validation/capture_00615_초1-2_6단원_덧셈과뺄셈_3__1회_p02_문항03.png",
      "upload_path": "/Users/juhwigeun/Library/Application Support/CocoAIStudy/uploads/6a7499b4ed4a_capture_00615_초1-2_6단원_덧셈과뺄셈_3__1회_p02_문항03.png",
      "upload_relative_path": "/Users/juhwigeun/Library/Application Support/CocoAIStudy/uploads/6a7499b4ed4a_capture_00615_초1-2_6단원_덧셈과뺄셈_3__1회_p02_문항03.png",
      "status": "ok",
      "issues": [],
      "math_topic": "arithmetic",
      "display_topic": "arithmetic",
      "problem_text": "12 - □ = 6, 12 - □ = 5, 12 - □ = 4, 12 - □ = 3에 알맞은 수를 쓰세요.",
      "expressions": [
        "answer_text=6, 7, 8, 9",
        "answer=13",
        "answer=6",
        "answer=7",
        "answer=8"
      ],
      "computed_answer": "6, 7, 8, 9",
      "matched_choice": "",
      "solver_name": "visual_template_solver",
      "validation_status": "verified",
      "problem_number": 13,
      "reference_answer": "6, 7, 8, 9",
      "pdf_card_text": "13. 안에 알맞은 수를 써넣으세요.",
      "source_preview": "12 - □ = 6, 12 - □ = 5, 12 - □ = 4, 12 - □ = 3에 알맞은 수를 쓰세요. 13. 안에 알맞은 수를 써넣으세요. 12- =6 12- =5 12- =4 13 - =3 13. | ㅣ 안에 알맞은 수를 써넣으세요. 19-| |=6 2-[ |=5 18-| ]=4 12-[ |=3 0 13. 안에 알맞은 수를 써넣으세요. 12- =6 12- =5 12- =4 13 ...",
      "elapsed_seconds": 0.519
    },
    {
      "index": 616,
      "case_id": "초1-2_6단원_덧셈과뺄셈(3)_1회_p02_capture_q04",
      "band": "초등",
      "grade": 1,
      "source_kind": "coco_app_capture",
      "image_path": "/Users/juhwigeun/Library/Application Support/CocoAIStudy/captures/validation_segments/c42138729b20/초1-2_6단원_덧셈과뺄셈_3__1회_p02_문항04.png",
      "relative_path": "/Users/juhwigeun/Library/Application Support/CocoAIStudy/captures/validation_segments/c42138729b20/초1-2_6단원_덧셈과뺄셈_3__1회_p02_문항04.png",
      "pdf_path": "02.학습문제/05.문제은행/01.초등/1학년/PDF/skai_0104_무료_수학프린트_학습지_[단원평가_1회]_초1-2_Ⅵ._덧셈과_뺄셈(3)_[무료_수학_프린트_학습지_-_단원평가]_초등_1학년__초1-2-6.덧셈과_뺄셈(3)_[1회].pdf",
      "title_slug": "초1-2_6단원_덧셈과뺄셈(3)_1회",
      "source_page": 2,
      "page_count": 3,
      "parent_page_index": 82,
      "parent_relative_path": "02.학습문제/05.문제은행/01.초등/1학년/EDITE/초1-2_6단원_덧셈과뺄셈(3)_1회_p02.png",
      "problem_card_index": 4,
      "problem_card_label": "04",
      "problem_card_bbox": [
        649,
        0,
        1326,
        311
      ],
      "expected_problem_number": 14,
      "capture_file_id": "645b4ab6890a",
      "capture_file_name": "capture_00616_초1-2_6단원_덧셈과뺄셈_3__1회_p02_문항04.png",
      "capture_path": "/Users/juhwigeun/Library/Application Support/CocoAIStudy/captures/validation/capture_00616_초1-2_6단원_덧셈과뺄셈_3__1회_p02_문항04.png",
      "upload_path": "/Users/juhwigeun/Library/Application Support/CocoAIStudy/uploads/645b4ab6890a_capture_00616_초1-2_6단원_덧셈과뺄셈_3__1회_p02_문항04.png",
      "upload_relative_path": "/Users/juhwigeun/Library/Application Support/CocoAIStudy/uploads/645b4ab6890a_capture_00616_초1-2_6단원_덧셈과뺄셈_3__1회_p02_문항04.png",
      "status": "ok",
      "issues": [],
      "math_topic": "arithmetic",
      "display_topic": "probability",
      "problem_text": "수 카드 8, 4, 1 중 2장을 뽑아 가장 작은 몇십몇을 만들었습니다. 만든 수와 남은 수의 차를 구하세요.",
      "expressions": [
        "answer=6"
      ],
      "computed_answer": "6",
      "matched_choice": "",
      "solver_name": "table_lookup_solver",
      "validation_status": "verified",
      "problem_number": 14,
      "reference_answer": "6",
      "pdf_card_text": "14. 수 카드 중 2 장을 뽑아 가장 작은 몇십몇을 만들었습니다. 만든 수와 남은 수의 차는 얼마 입니까? 8 4 1",
      "source_preview": "수 카드 8, 4, 1 중 2장을 뽑아 가장 작은 몇십몇을 만들었습니다. 만든 수와 남은 수의 차를 구하세요. 14,4 카드 중 2장을 뽑아 가장 작은 몇십몇을 1 14.4% 카드 중 2장을 뽑아 가장 작은 BUSS 14, 수 카드 중 2장을 뽑아 가장 작은 SUBS 14,4 카드 중 2장을 뽑아 가장 작은 몇십몇을 1 14.4% 카드 중 2장을 뽑아 가장 작은 BUSS 14, 수 카드...",
      "elapsed_seconds": 0.564
    },
    {
      "index": 617,
      "case_id": "초1-2_6단원_덧셈과뺄셈(3)_1회_p02_capture_q05",
      "band": "초등",
      "grade": 1,
      "source_kind": "coco_app_capture",
      "image_path": "/Users/juhwigeun/Library/Application Support/CocoAIStudy/captures/validation_segments/c42138729b20/초1-2_6단원_덧셈과뺄셈_3__1회_p02_문항05.png",
      "relative_path": "/Users/juhwigeun/Library/Application Support/CocoAIStudy/captures/validation_segments/c42138729b20/초1-2_6단원_덧셈과뺄셈_3__1회_p02_문항05.png",
      "pdf_path": "02.학습문제/05.문제은행/01.초등/1학년/PDF/skai_0104_무료_수학프린트_학습지_[단원평가_1회]_초1-2_Ⅵ._덧셈과_뺄셈(3)_[무료_수학_프린트_학습지_-_단원평가]_초등_1학년__초1-2-6.덧셈과_뺄셈(3)_[1회].pdf",
      "title_slug": "초1-2_6단원_덧셈과뺄셈(3)_1회",
      "source_page": 2,
      "page_count": 3,
      "parent_page_index": 82,
      "parent_relative_path": "02.학습문제/05.문제은행/01.초등/1학년/EDITE/초1-2_6단원_덧셈과뺄셈(3)_1회_p02.png",
      "problem_card_index": 5,
      "problem_card_label": "05",
      "problem_card_bbox": [
        649,
        311,
        1326,
        559
      ],
      "expected_problem_number": 15,
      "capture_file_id": "aa6fa9eabcae",
      "capture_file_name": "capture_00617_초1-2_6단원_덧셈과뺄셈_3__1회_p02_문항05.png",
      "capture_path": "/Users/juhwigeun/Library/Application Support/CocoAIStudy/captures/validation/capture_00617_초1-2_6단원_덧셈과뺄셈_3__1회_p02_문항05.png",
      "upload_path": "/Users/juhwigeun/Library/Application Support/CocoAIStudy/uploads/aa6fa9eabcae_capture_00617_초1-2_6단원_덧셈과뺄셈_3__1회_p02_문항05.png",
      "upload_relative_path": "/Users/juhwigeun/Library/Application Support/CocoAIStudy/uploads/aa6fa9eabcae_capture_00617_초1-2_6단원_덧셈과뺄셈_3__1회_p02_문항05.png",
      "status": "ok",
      "issues": [],
      "math_topic": "arithmetic",
      "display_topic": "arithmetic",
      "problem_text": "11 - 6, 15 - 7, 7 + 4 중 계산 결과가 8인 것을 찾으세요.",
      "expressions": [
        "answer_text=15 - 7에 ○표",
        "11-6 15-7 7+4"
      ],
      "computed_answer": "15 - 7에 ○표",
      "matched_choice": "",
      "solver_name": "visual_template_solver",
      "validation_status": "verified",
      "problem_number": 15,
      "reference_answer": "15 + 7 에 ○표",
      "pdf_card_text": "( ) 15. 계산 결과가 8 인 것을 찾아 ○표 하세요. 11 + 6 15 + 7 74",
      "source_preview": "11 - 6, 15 - 7, 7 + 4 중 계산 결과가 8인 것을 찾으세요. 15. 계산 결과가 8인 것을 찾아 ○표 하세요. 11-6 15-7 7+4 15. 계산 결과가 sel 것을 찾아 ○표 하세요. 15. 계산 결과가 8인 것을 찾아 ○표 하세요. 11-6 15-7 7+4 15. 계산 결과가 sel 것을 찾아 ○표 하세요.",
      "elapsed_seconds": 0.455
    },
    {
      "index": 618,
      "case_id": "초1-2_6단원_덧셈과뺄셈(3)_1회_p02_capture_q06",
      "band": "초등",
      "grade": 1,
      "source_kind": "coco_app_capture",
      "image_path": "/Users/juhwigeun/Library/Application Support/CocoAIStudy/captures/validation_segments/c42138729b20/초1-2_6단원_덧셈과뺄셈_3__1회_p02_문항06.png",
      "relative_path": "/Users/juhwigeun/Library/Application Support/CocoAIStudy/captures/validation_segments/c42138729b20/초1-2_6단원_덧셈과뺄셈_3__1회_p02_문항06.png",
      "pdf_path": "02.학습문제/05.문제은행/01.초등/1학년/PDF/skai_0104_무료_수학프린트_학습지_[단원평가_1회]_초1-2_Ⅵ._덧셈과_뺄셈(3)_[무료_수학_프린트_학습지_-_단원평가]_초등_1학년__초1-2-6.덧셈과_뺄셈(3)_[1회].pdf",
      "title_slug": "초1-2_6단원_덧셈과뺄셈(3)_1회",
      "source_page": 2,
      "page_count": 3,
      "parent_page_index": 82,
      "parent_relative_path": "02.학습문제/05.문제은행/01.초등/1학년/EDITE/초1-2_6단원_덧셈과뺄셈(3)_1회_p02.png",
      "problem_card_index": 6,
      "problem_card_label": "06",
      "problem_card_bbox": [
        649,
        559,
        1326,
        795
      ],
      "expected_problem_number": 16,
      "capture_file_id": "9e535e3c32c5",
      "capture_file_name": "capture_00618_초1-2_6단원_덧셈과뺄셈_3__1회_p02_문항06.png",
      "capture_path": "/Users/juhwigeun/Library/Application Support/CocoAIStudy/captures/validation/capture_00618_초1-2_6단원_덧셈과뺄셈_3__1회_p02_문항06.png",
      "upload_path": "/Users/juhwigeun/Library/Application Support/CocoAIStudy/uploads/9e535e3c32c5_capture_00618_초1-2_6단원_덧셈과뺄셈_3__1회_p02_문항06.png",
      "upload_relative_path": "/Users/juhwigeun/Library/Application Support/CocoAIStudy/uploads/9e535e3c32c5_capture_00618_초1-2_6단원_덧셈과뺄셈_3__1회_p02_문항06.png",
      "status": "ok",
      "issues": [],
      "math_topic": "arithmetic",
      "display_topic": "arithmetic",
      "problem_text": "11에서 어떤 수를 뺐더니 5가 되었습니다. 어떤 수를 구하세요.",
      "expressions": [
        "answer=6"
      ],
      "computed_answer": "6",
      "matched_choice": "",
      "solver_name": "table_lookup_solver",
      "validation_status": "verified",
      "problem_number": 16,
      "reference_answer": "6",
      "pdf_card_text": "16. 11 에서 어떤 수를 뺐더니 5 가 되었습니다. 어떤 수를 구해 보세요. ( )",
      "source_preview": "11에서 어떤 수를 뺐더니 5가 되었습니다. 어떤 수를 구하세요. 16. 11어서 어떤 AB BCI] 5가 되었습니다, 16. 11에서 어떤 수를 CHL] 5가 되었습니다. 16. 11에서 어떤 수를 WEL) 5가 되었습니다. 16. 11어서 어떤 AB BCI] 5가 되었습니다, 16. 11에서 어떤 수를 CHL] 5가 되었습니다. 16. 11에서 어떤 수를 WEL) 5가 되었습니다.",
      "elapsed_seconds": 0.457
    },
    {
      "index": 619,
      "case_id": "초1-2_6단원_덧셈과뺄셈(3)_1회_p02_capture_q07",
      "band": "초등",
      "grade": 1,
      "source_kind": "coco_app_capture",
      "image_path": "/Users/juhwigeun/Library/Application Support/CocoAIStudy/captures/validation_segments/c42138729b20/초1-2_6단원_덧셈과뺄셈_3__1회_p02_문항07.png",
      "relative_path": "/Users/juhwigeun/Library/Application Support/CocoAIStudy/captures/validation_segments/c42138729b20/초1-2_6단원_덧셈과뺄셈_3__1회_p02_문항07.png",
      "pdf_path": "02.학습문제/05.문제은행/01.초등/1학년/PDF/skai_0104_무료_수학프린트_학습지_[단원평가_1회]_초1-2_Ⅵ._덧셈과_뺄셈(3)_[무료_수학_프린트_학습지_-_단원평가]_초등_1학년__초1-2-6.덧셈과_뺄셈(3)_[1회].pdf",
      "title_slug": "초1-2_6단원_덧셈과뺄셈(3)_1회",
      "source_page": 2,
      "page_count": 3,
      "parent_page_index": 82,
      "parent_relative_path": "02.학습문제/05.문제은행/01.초등/1학년/EDITE/초1-2_6단원_덧셈과뺄셈(3)_1회_p02.png",
      "problem_card_index": 7,
      "problem_card_label": "07",
      "problem_card_bbox": [
        649,
        795,
        1326,
        1077
      ],
      "expected_problem_number": 17,
      "capture_file_id": "2e8ad7d97be7",
      "capture_file_name": "capture_00619_초1-2_6단원_덧셈과뺄셈_3__1회_p02_문항07.png",
      "capture_path": "/Users/juhwigeun/Library/Application Support/CocoAIStudy/captures/validation/capture_00619_초1-2_6단원_덧셈과뺄셈_3__1회_p02_문항07.png",
      "upload_path": "/Users/juhwigeun/Library/Application Support/CocoAIStudy/uploads/2e8ad7d97be7_capture_00619_초1-2_6단원_덧셈과뺄셈_3__1회_p02_문항07.png",
      "upload_relative_path": "/Users/juhwigeun/Library/Application Support/CocoAIStudy/uploads/2e8ad7d97be7_capture_00619_초1-2_6단원_덧셈과뺄셈_3__1회_p02_문항07.png",
      "status": "ok",
      "issues": [],
      "math_topic": "arithmetic",
      "display_topic": "arithmetic",
      "problem_text": "스티커 6개를 붙인 후 5개를 더 붙였습니다. 모두 11개입니다.",
      "expressions": [
        "answer_text=11개"
      ],
      "computed_answer": "11개",
      "matched_choice": "",
      "solver_name": "visual_template_solver",
      "validation_status": "verified",
      "problem_number": 17,
      "reference_answer": "11 개",
      "pdf_card_text": "17. 윤희는 스티커북에 스티커를 6 개를 붙인 후 5 개를 더 붙였습니다. 스티커북에 붙인 스티커 는 모두 몇 개일까요? ( )",
      "source_preview": "스티커 6개를 붙인 후 5개를 더 붙였습니다. 모두 11개입니다. 17. 윤희는 스티커북에 스티커를 6개를 붙인 후 . 5개를 더 붙였습니다. 스티커북에 붙인 스티커 5개를 더 붙였습니다. 스티커북에 붙인 스티커 17. 윤희는 스티커북에 스티커를 6개를 붙인 후 . 5개를 더 붙였습니다. 스티커북에 붙인 스티커 5개를 더 붙였습니다. 스티커북에 붙인 스티커",
      "elapsed_seconds": 0.578
    },
    {
      "index": 620,
      "case_id": "초1-2_6단원_덧셈과뺄셈(3)_1회_p02_capture_q08",
      "band": "초등",
      "grade": 1,
      "source_kind": "coco_app_capture",
      "image_path": "/Users/juhwigeun/Library/Application Support/CocoAIStudy/captures/validation_segments/c42138729b20/초1-2_6단원_덧셈과뺄셈_3__1회_p02_문항08.png",
      "relative_path": "/Users/juhwigeun/Library/Application Support/CocoAIStudy/captures/validation_segments/c42138729b20/초1-2_6단원_덧셈과뺄셈_3__1회_p02_문항08.png",
      "pdf_path": "02.학습문제/05.문제은행/01.초등/1학년/PDF/skai_0104_무료_수학프린트_학습지_[단원평가_1회]_초1-2_Ⅵ._덧셈과_뺄셈(3)_[무료_수학_프린트_학습지_-_단원평가]_초등_1학년__초1-2-6.덧셈과_뺄셈(3)_[1회].pdf",
      "title_slug": "초1-2_6단원_덧셈과뺄셈(3)_1회",
      "source_page": 2,
      "page_count": 3,
      "parent_page_index": 82,
      "parent_relative_path": "02.학습문제/05.문제은행/01.초등/1학년/EDITE/초1-2_6단원_덧셈과뺄셈(3)_1회_p02.png",
      "problem_card_index": 8,
      "problem_card_label": "08",
      "problem_card_bbox": [
        649,
        1077,
        1326,
        1360
      ],
      "expected_problem_number": 18,
      "capture_file_id": "83cdfe374106",
      "capture_file_name": "capture_00620_초1-2_6단원_덧셈과뺄셈_3__1회_p02_문항08.png",
      "capture_path": "/Users/juhwigeun/Library/Application Support/CocoAIStudy/captures/validation/capture_00620_초1-2_6단원_덧셈과뺄셈_3__1회_p02_문항08.png",
      "upload_path": "/Users/juhwigeun/Library/Application Support/CocoAIStudy/uploads/83cdfe374106_capture_00620_초1-2_6단원_덧셈과뺄셈_3__1회_p02_문항08.png",
      "upload_relative_path": "/Users/juhwigeun/Library/Application Support/CocoAIStudy/uploads/83cdfe374106_capture_00620_초1-2_6단원_덧셈과뺄셈_3__1회_p02_문항08.png",
      "status": "ok",
      "issues": [],
      "math_topic": "arithmetic",
      "display_topic": "arithmetic",
      "problem_text": "수호는 딸기 7개와 귤 6개, 유진이는 딸기 9개와 귤 3개를 먹었습니다. 먹은 과일 수의 합이 더 큰 학생은 수호입니다.",
      "expressions": [
        "answer_text=수호"
      ],
      "computed_answer": "수호",
      "matched_choice": "",
      "solver_name": "visual_template_solver",
      "validation_status": "verified",
      "problem_number": 18,
      "reference_answer": "수호",
      "pdf_card_text": "19. 수진이는 사탕 12 개 중에서 5 개를 먹었습니",
      "source_preview": "수호는 딸기 7개와 귤 6개, 유진이는 딸기 9개와 귤 3개를 먹었습니다. 먹은 과일 수의 합이 더 큰 학생은 수호입니다. 18. ss S| 7개와 SB 6개를 먹었고, 유진 이는 딸기 9개와 글 3개를 먹었습니다. 먹는 18. 수호는 딸기 7개와 글 6개를 먹었고, 유진 18. 수호는 딸기 7개와 글 oS 먹었고, 유진 18. ss S| 7개와 SB 6개를 먹었고, 유진 이는 딸기 9...",
      "elapsed_seconds": 0.644
    }
  ]
}